mintersdk/__init__.py
mintersdk/minterapi.py
mintersdk/shortcuts.py
mintersdk/sdk/__init__.py
mintersdk/sdk/check.py
mintersdk/sdk/deeplink.py
mintersdk/sdk/transactions.py
mintersdk/sdk/wallet.py
mintersdk/test/__init__.py
mintersdk/test/test_check.py
mintersdk/test/test_deeplink.py
mintersdk/test/test_transactions.py
mintersdk/test/test_wallet.py
minter_sdk-1.0.34.dist-info/LICENSE
minter_sdk-1.0.34.dist-info/METADATA
minter_sdk-1.0.34.dist-info/WHEEL
minter_sdk-1.0.34.dist-info/top_level.txt
minter_sdk-1.0.34.dist-info/RECORD
