Metadata-Version: 2.1
Name: minter-sdk
Version: 1.0.34
Summary: Python SDK for Minter Network
Home-page: https://github.com/U-node/minter-sdk
Author: U-node Team
Author-email: rymka1989@gmail.com
License: UNKNOWN
Platform: UNKNOWN
Classifier: Programming Language :: Python :: 3
Classifier: License :: OSI Approved :: MIT License
Classifier: Operating System :: OS Independent
Requires-Dist: rlp
Requires-Dist: sslcrypto
Requires-Dist: mnemonic
Requires-Dist: pysha3
Requires-Dist: requests
Requires-Dist: pyqrcode
Requires-Dist: deprecated
